aws_lambda/__init__.py
aws_lambda/__version__.py
aws_lambda/apig/__init__.py
aws_lambda_handler-0.0.4.dist-info/METADATA
aws_lambda_handler-0.0.4.dist-info/RECORD
aws_lambda_handler-0.0.4.dist-info/WHEEL
aws_lambda_handler-0.0.4.dist-info/top_level.txt
pal/__init__.py
pal/__version__.py
pal/apig/__init__.py
