Metadata-Version: 2.1
Name: aws-lambda-handler
Version: 0.0.4
Summary: Better AWS Lambda handlers.
Home-page: https://github.com/hmngwy/py-aws-lambda-handler/
Author: Pat Ambrosio
Author-email: patambrosio@me.com
License: MIT
Platform: UNKNOWN
Classifier: License :: OSI Approved :: GNU General Public License v2 (GPLv2)
Classifier: Programming Language :: Python
Classifier: Programming Language :: Python :: 3
Classifier: Programming Language :: Python :: 3.6
Classifier: Programming Language :: Python :: Implementation :: CPython
Classifier: Programming Language :: Python :: Implementation :: PyPy
Requires-Python: >=3.6.0
Requires-Dist: inflection
Requires-Dist: simplejson
Requires-Dist: namedtupled
Requires-Dist: cached-property
